{
  "host": "127.0.0.1",
  "port": 8778,
  "hceCard": {
    "firstName": "Cristian",
    "lastName": "Iordache",
    "expMonth": 11,
    "expYear": 2018,
    "cardNumber": "5555555555554444",
    "type": "Card",
    "cvc": "113"
  },
  "pspConfig": {
    // Worldpay Online Payments
    "psp_name": "worldpayonlinepayments",
    "api_endpoint": "https://api.worldpay.com/v1"

    // Worldpay Total US / SecureNet
    // "PSP_NAME": "securenet",
    // "API_ENDPOINT": "https://gwapi.demo.securenet.com/api",
    // "APP_VERSION": "0.1",
    // "DEVELOPER_ID": "12345678",
  }
}
